virgil_crypto_lib-0.16.0.data/purelib/virgil_crypto_lib/__init__.py
virgil_crypto_lib-0.16.0.data/purelib/virgil_crypto_lib/_libs/__init__.py
virgil_crypto_lib-0.16.0.data/purelib/virgil_crypto_lib/_libs/low_level_libs.py
virgil_crypto_lib-0.16.0.data/purelib/virgil_crypto_lib/_libs/vsc_common.dll
virgil_crypto_lib-0.16.0.data/purelib/virgil_crypto_lib/_libs/vsc_common.lib
virgil_crypto_lib-0.16.0.data/purelib/virgil_crypto_lib/_libs/vsc_foundation.dll
virgil_crypto_lib-0.16.0.data/purelib/virgil_crypto_lib/_libs/vsc_foundation.lib
virgil_crypto_lib-0.16.0.data/purelib/virgil_crypto_lib/_libs/vsc_phe.dll
virgil_crypto_lib-0.16.0.data/purelib/virgil_crypto_lib/_libs/vsc_phe.lib
virgil_crypto_lib-0.16.0.data/purelib/virgil_crypto_lib/_libs/vsc_ratchet.dll
virgil_crypto_lib-0.16.0.data/purelib/virgil_crypto_lib/_libs/vsc_ratchet.lib
virgil_crypto_lib-0.16.0.data/purelib/virgil_crypto_lib/common/__init__.py
virgil_crypto_lib-0.16.0.data/purelib/virgil_crypto_lib/common/_c_bridge/__init__.py
virgil_crypto_lib-0.16.0.data/purelib/virgil_crypto_lib/common/_c_bridge/_buffer.py
virgil_crypto_lib-0.16.0.data/purelib/virgil_crypto_lib/common/_c_bridge/_data.py
virgil_crypto_lib-0.16.0.data/purelib/virgil_crypto_lib/common/_c_bridge/_vsc_buffer.py
virgil_crypto_lib-0.16.0.data/purelib/virgil_crypto_lib/common/_c_bridge/_vsc_data.py
virgil_crypto_lib-0.16.0.data/purelib/virgil_crypto_lib/foundation/__init__.py
virgil_crypto_lib-0.16.0.data/purelib/virgil_crypto_lib/foundation/aes256_cbc.py
virgil_crypto_lib-0.16.0.data/purelib/virgil_crypto_lib/foundation/aes256_gcm.py
virgil_crypto_lib-0.16.0.data/purelib/virgil_crypto_lib/foundation/alg.py
virgil_crypto_lib-0.16.0.data/purelib/virgil_crypto_lib/foundation/alg_factory.py
virgil_crypto_lib-0.16.0.data/purelib/virgil_crypto_lib/foundation/alg_id.py
virgil_crypto_lib-0.16.0.data/purelib/virgil_crypto_lib/foundation/alg_info.py
virgil_crypto_lib-0.16.0.data/purelib/virgil_crypto_lib/foundation/alg_info_der_deserializer.py
virgil_crypto_lib-0.16.0.dist-info/METADATA
virgil_crypto_lib-0.16.0.dist-info/WHEEL
virgil_crypto_lib-0.16.0.dist-info/top_level.txt
virgil_crypto_lib-0.16.0.dist-info/RECORD
