Metadata-Version: 1.1
Name: virgil-crypto-lib
Version: 0.16.0
Summary: 
Home-page: https://virgilsecurity.com
Author: Virgil Security
Author-email: support@virgilsecurity.com
License: BSD 3-Clause
Project-URL: Tracker, https://github.com/VirgilSecurity/virgil-crypto-c/issues
Project-URL: Source, https://github.com/VirgilSecurity/virgil-crypto-c
Project-URL: Documentation, https://developer.virgilsecurity.com
Platform: UNKNOWN
Classifier: Development Status :: 5 - Production/Stable
Classifier: License :: OSI Approved :: BSD License
Classifier: Natural Language :: English
Classifier: Intended Audience :: Developers
Classifier: Programming Language :: C
Classifier: Programming Language :: Python :: 2.7
Classifier: Programming Language :: Python :: 3.4
Classifier: Programming Language :: Python :: 3.5
Classifier: Programming Language :: Python :: 3.6
Classifier: Programming Language :: Python :: 3.7
Classifier: Topic :: Security
Classifier: Topic :: Security :: Cryptography
Classifier: Topic :: Software Development :: Libraries :: Application Frameworks
Classifier: Topic :: Software Development :: Libraries :: Python Modules
